[
  {
    "date": "2025-04-02",
    "time": "1-3p",
    "description": "Group Hacky Hours",
    "zoom": "https://stanford.zoom.us/j/96407968979?pwd=NFeSzeNEeGcfQgfIM33RilLLVcBzbh.1"
  },
  {
    "date": "2025-04-03",
    "time": "2-5p",
    "description": "Group Hacky Hours",
    "zoom": "https://stanford.zoom.us/j/99006781482?pwd=Zm93FerRxYFZzDkaJ9fUJplrsJ9oLC.1"
  },
  {
    "date": "2025-04-04",
    "time": "2-5p",
    "description":"Group Hacky Hours",
    "zoom": "https://stanford.zoom.us/j/92054325204?pwd=Ak50R8VHl3XVz47ZDchyDRMJrBKeyh.1"
  },
  {
    "date": "2025-04-09",
    "time": "1:15-4:15p",
    "description": "Group Hacky Hours",
    "zoom": "https://stanford.zoom.us/j/96407968979?pwd=NFeSzeNEeGcfQgfIM33RilLLVcBzbh.1"
  },
  {
    "date": "2025-04-10",
    "time": "1-4p",
    "description": "Group Hacky Hours",
    "zoom": "https://stanford.zoom.us/j/96407968979?pwd=NFeSzeNEeGcfQgfIM33RilLLVcBzbh.1"
  },
  {
    "date": "2025-04-11",
    "time": "12-2p",
    "description": "Group Hacky Hours",
    "zoom": "https://stanford.zoom.us/j/96407968979?pwd=NFeSzeNEeGcfQgfIM33RilLLVcBzbh.1"
  },
  {
    "date": "2025-04-17",
    "time": "12-4p",
    "description": "Group Hacky Hours",
    "zoom": "https://stanford.zoom.us/j/96407968979?pwd=NFeSzeNEeGcfQgfIM33RilLLVcBzbh.1"
  },
  {
    "date": "2025-04-18",
    "time": "9:30a-12:30p",
    "description": "Group Hacky Hours",
    "zoom": "https://stanford.zoom.us/j/96407968979?pwd=NFeSzeNEeGcfQgfIM33RilLLVcBzbh.1"
  },
  {
    "date": "2025-04-23",
    "time": "2-4p",
    "description": "Group Hacky Hours",
    "zoom": "https://stanford.zoom.us/j/96407968979?pwd=NFeSzeNEeGcfQgfIM33RilLLVcBzbh.1"
  },
  {
    "date": "2025-04-24",
    "time": "11:15a-1:45p",
    "description": "Group Hacky Hours",
    "zoom": "https://stanford.zoom.us/j/96407968979?pwd=NFeSzeNEeGcfQgfIM33RilLLVcBzbh.1"
  },
  {
    "date": "2025-04-24",
    "time": "2:15-4:45p",
    "description": "Group Hacky Hours",
    "zoom": "https://stanford.zoom.us/j/96407968979?pwd=NFeSzeNEeGcfQgfIM33RilLLVcBzbh.1"
  },
  {
    "date": "2025-04-30",
    "time": "<s>12-3p</s> (CANCELLED)",
    "description": "<s>Group Hacky Hours</s>",
    "zoom": ""
  },
  {
    "date": "2025-05-01",
    "time": "1-6p",
    "description": "Group Hacky Hours",
    "zoom": "https://stanford.zoom.us/j/96407968979?pwd=NFeSzeNEeGcfQgfIM33RilLLVcBzbh.1"
  },
  {
    "date": "2025-05-07",
    "time": "3:30-4:30p",
    "description": "Group Hacky Hours",
    "zoom": "https://stanford.zoom.us/j/96407968979?pwd=NFeSzeNEeGcfQgfIM33RilLLVcBzbh.1"
  },
  {
    "date": "2025-05-08",
    "time": "1:30-5:30p",
    "description": "Group Hacky Hours",
    "zoom": "https://stanford.zoom.us/j/96407968979?pwd=NFeSzeNEeGcfQgfIM33RilLLVcBzbh.1"
  },
  {
    "date": "2025-05-09",
    "time": "9:30a-12:30p",
    "description": "Group Hacky Hours",
    "zoom": "https://stanford.zoom.us/j/96407968979?pwd=NFeSzeNEeGcfQgfIM33RilLLVcBzbh.1"
  }
]
